RHaP/__init__.py
RHaP/branching.py
RHaP/crack_path.py
RHaP/cropping_functions.py
RHaP/image_processing.py
RHaP/import_image.py
RHaP/plot_functions.py
RHaP/radial_hydride_fraction.py
RHaP-0.2.dist-info/LICENSE
RHaP-0.2.dist-info/METADATA
RHaP-0.2.dist-info/WHEEL
RHaP-0.2.dist-info/top_level.txt
RHaP-0.2.dist-info/RECORD
