Metadata-Version: 2.1
Name: RHaP
Version: 0.2
Summary: A python library to analyse hydride morphology present in light optical and scanning electron micrographs.
Home-page: UNKNOWN
Author: Mia Maric, Rhys Thomas, Michael D. Atkinson
Author-email: mia.maric@manchester.ac.uk
License: UNKNOWN
Project-URL: GitHub, https://github.com/miamaric12/Radial_Hydride_Code
Keywords: micrograph,zirconium,hydride
Platform: UNKNOWN
Classifier: Intended Audience :: Science/Research
Classifier: Topic :: Scientific/Engineering
Classifier: Topic :: Scientific/Engineering :: Information Analysis
Classifier: Development Status :: 4 - Beta
Classifier: Natural Language :: English
Classifier: Operating System :: OS Independent
Classifier: Programming Language :: Python :: 3
Classifier: Programming Language :: Python :: 3.5
Classifier: Programming Language :: Python :: 3.6
Classifier: Programming Language :: Python :: 3.7
Classifier: Programming Language :: Python :: 3.8
Classifier: Framework :: IPython
Classifier: Framework :: Jupyter
Classifier: Framework :: Matplotlib
Requires-Python: >=3.5
Requires-Dist: scipy
Requires-Dist: numpy
Requires-Dist: matplotlib (>=3.0.0)
Requires-Dist: scikit-image
Requires-Dist: numba
Requires-Dist: skan
Requires-Dist: toolz
Requires-Dist: matplotlib-scalebar
Requires-Dist: networkx
Requires-Dist: jupyter
